base_ouro/__init__.py
base_ouro/base_ouro.py
base_ouro-12.0.dist-info/licenses/LICENSE.txt
base_ouro-12.0.dist-info/METADATA
base_ouro-12.0.dist-info/WHEEL
base_ouro-12.0.dist-info/top_level.txt
base_ouro-12.0.dist-info/RECORD
