Metadata-Version: 2.4
Name: base_ouro
Version: 12.0
Summary: Conversor utilizado para a geração da Base Ouro
Author: Gabriel Ernesto Barboza Pereira
Author-email: ernesto.gabriel@pucpr.br
License: MIT
Keywords: conversor base_ouro
License-File: LICENSE.txt
Dynamic: author
Dynamic: author-email
Dynamic: description
Dynamic: description-content-type
Dynamic: keywords
Dynamic: license
Dynamic: license-file
Dynamic: summary
